constants.py
main.py
image_namer-2.1.0.dist-info/licenses/LICENSE
operations/__init__.py
operations/analyze_image.py
operations/assess_name.py
operations/assess_name_spec.py
operations/cache.py
operations/cache_spec.py
operations/find_references.py
operations/find_references_spec.py
operations/generate_name.py
operations/generate_name_spec.py
operations/models.py
operations/models_spec.py
operations/update_references.py
operations/update_references_spec.py
ui/__init__.py
ui/main.py
ui/main_window.py
ui/settings.py
ui/dialogs/__init__.py
ui/models/__init__.py
ui/models/ui_models.py
ui/resources/__init__.py
ui/widgets/__init__.py
ui/workers/__init__.py
ui/workers/cache_loader.py
ui/workers/rename_worker.py
utils/__init__.py
utils/fs.py
utils/fs_spec.py
utils/next_available_name_spec.py
image_namer-2.1.0.dist-info/METADATA
image_namer-2.1.0.dist-info/WHEEL
image_namer-2.1.0.dist-info/entry_points.txt
image_namer-2.1.0.dist-info/top_level.txt
image_namer-2.1.0.dist-info/RECORD
