Metadata-Version: 2.4
Name: image-namer
Version: 2.1.0
Summary: Rename image files based on their visual contents using AI vision models.
Author-email: Stacey Vetzal <stacey@vetzal.com>
License: MIT License
Project-URL: Homepage, https://github.com/svetzal/image-namer
Project-URL: Issues, https://github.com/svetzal/image-namer/issues
Keywords: images,renamer,cli,gui
Classifier: Programming Language :: Python :: 3
Classifier: Programming Language :: Python :: 3 :: Only
Classifier: Programming Language :: Python :: 3.13
Classifier: License :: OSI Approved :: MIT License
Classifier: Intended Audience :: End Users/Desktop
Classifier: Intended Audience :: Developers
Classifier: Topic :: Multimedia :: Graphics
Classifier: Topic :: Utilities
Requires-Python: >=3.13
License-File: LICENSE
Requires-Dist: typer>=0.12.5
Requires-Dist: rich>=13.7.0
Requires-Dist: pydantic>=2.9.0
Requires-Dist: mojentic>=0.8.4
Provides-Extra: dev
Requires-Dist: pytest>=8.2; extra == "dev"
Requires-Dist: pytest-cov>=5.0; extra == "dev"
Requires-Dist: pytest-mock>=3.14; extra == "dev"
Requires-Dist: flake8>=7.1; extra == "dev"
Requires-Dist: flake8-pyproject>=1.2; extra == "dev"
Requires-Dist: mypy>=1.13; extra == "dev"
Requires-Dist: mkdocs>=1.6; extra == "dev"
Requires-Dist: mkdocs-material>=9.5; extra == "dev"
Provides-Extra: gui
Requires-Dist: PySide6>=6.7; extra == "gui"
Dynamic: license-file
